[{"id":"18.02.17.2001","district_id":"18.02.17","name":"Tanjung Ratu Ilir"},{"id":"18.02.17.2002","district_id":"18.02.17","name":"Candi Rejo"},{"id":"18.02.17.2003","district_id":"18.02.17","name":"Banjar Ratu"},{"id":"18.02.17.2004","district_id":"18.02.17","name":"Banjar Kerta Rahayu"},{"id":"18.02.17.2005","district_id":"18.02.17","name":"Lempuyang Bandar"},{"id":"18.02.17.2006","district_id":"18.02.17","name":"Purnama Tunggal"},{"id":"18.02.17.2007","district_id":"18.02.17","name":"Banjar Rejo"},{"id":"18.02.17.2008","district_id":"18.02.17","name":"Putra Lempuyang"}]