[{"id":"18.71.13.1001","district_id":"18.71.13","name":"Sumber Rejo"},{"id":"18.71.13.1003","district_id":"18.71.13","name":"Beringin Jaya"},{"id":"18.71.13.1004","district_id":"18.71.13","name":"Kemiling Permai"},{"id":"18.71.13.1005","district_id":"18.71.13","name":"Sumber Agung"},{"id":"18.71.13.1006","district_id":"18.71.13","name":"Kedaung"},{"id":"18.71.13.1007","district_id":"18.71.13","name":"Pinang Jaya"},{"id":"18.71.13.1008","district_id":"18.71.13","name":"Sumberrejo Sejahtera"},{"id":"18.71.13.1009","district_id":"18.71.13","name":"Kemiling Raya"},{"id":"18.71.13.1010","district_id":"18.71.13","name":"Beringin Raya"}]