[{"id":"36.01.08.2001","district_id":"36.01.08","name":"Pasanggrahan"},{"id":"36.01.08.2002","district_id":"36.01.08","name":"Sukasaba"},{"id":"36.01.08.2005","district_id":"36.01.08","name":"Gunungbatu"},{"id":"36.01.08.2006","district_id":"36.01.08","name":"Panacaran"},{"id":"36.01.08.2007","district_id":"36.01.08","name":"Curuglanglang"},{"id":"36.01.08.2008","district_id":"36.01.08","name":"Munjul"},{"id":"36.01.08.2009","district_id":"36.01.08","name":"Cibitung"},{"id":"36.01.08.2011","district_id":"36.01.08","name":"Kotadukuh"},{"id":"36.01.08.2018","district_id":"36.01.08","name":"Lebak"}]