[{"id":"73.10.13.2001","district_id":"73.10.13","name":"Mattiro Kanja"},{"id":"73.10.13.2002","district_id":"73.10.13","name":"Mattiro Baji"},{"id":"73.10.13.2003","district_id":"73.10.13","name":"Mattiro Bulu"},{"id":"73.10.13.2004","district_id":"73.10.13","name":"Mattiro Bombang"},{"id":"73.10.13.2005","district_id":"73.10.13","name":"Mattiro Labangeng"},{"id":"73.10.13.2006","district_id":"73.10.13","name":"Mattiro Uleng"},{"id":"73.10.13.2007","district_id":"73.10.13","name":"Mattiro Walie"}]