[{"id":"74.15.05.2001","district_id":"74.15.05","name":"Molona"},{"id":"74.15.05.2002","district_id":"74.15.05","name":"Mbanua"},{"id":"74.15.05.2003","district_id":"74.15.05","name":"Lalole"},{"id":"74.15.05.2004","district_id":"74.15.05","name":"Watuampara"},{"id":"74.15.05.2005","district_id":"74.15.05","name":"Katampe"},{"id":"74.15.05.2006","district_id":"74.15.05","name":"Lamaninggara"},{"id":"74.15.05.2007","district_id":"74.15.05","name":"Kamoali"},{"id":"74.15.05.2008","district_id":"74.15.05","name":"Mokobeau"}]