[{"id":"18.13.09.2001","district_id":"18.13.09","name":"Sumber Agung"},{"id":"18.13.09.2002","district_id":"18.13.09","name":"Ulok Mukti"},{"id":"18.13.09.2003","district_id":"18.13.09","name":"Negeri Ratu Ngambur"},{"id":"18.13.09.2004","district_id":"18.13.09","name":"Pekon Mon"},{"id":"18.13.09.2005","district_id":"18.13.09","name":"Gedung Cahya Kuningan"},{"id":"18.13.09.2006","district_id":"18.13.09","name":"Suka Banjar"},{"id":"18.13.09.2007","district_id":"18.13.09","name":"Suka Negara"},{"id":"18.13.09.2008","district_id":"18.13.09","name":"Muara Tembulih"},{"id":"18.13.09.2009","district_id":"18.13.09","name":"Bumi Ratu"}]